willse_backgammon/Main.py
willse_backgammon/Manual.py
willse_backgammon/Network.py
willse_backgammon/__init__.py
willse_backgammon/AI_Agents/Network_Type1.py
willse_backgammon/AI_Agents/Network_Type2.py
willse_backgammon/AI_Agents/Pick_Best_Pip.py
willse_backgammon/AI_Agents/TreeSearchI.py
willse_backgammon/AI_Agents/__init__.py
willse_backgammon/AI_Agents/Data_Sets/Network_Type1_Data.db
willse_backgammon/AI_Agents/Data_Sets/Network_Type2_Data.db
willse_backgammon/AI_Agents/Data_Sets/data_set_1.csv
willse_backgammon/AI_Agents/__pycache__/Network_Type1.cpython-310.pyc
willse_backgammon/AI_Agents/__pycache__/Pick_Best_Pip.cpython-310.pyc
willse_backgammon/AI_Agents/__pycache__/TreeSearchI.cpython-310.pyc
willse_backgammon/AI_Agents/__pycache__/__init__.cpython-310.pyc
willse_backgammon/Images/Move.png
willse_backgammon/Images/Submove.png
willse_backgammon/Images/darkPiece.png
willse_backgammon/Images/darkPiece2.png
willse_backgammon/Images/darkPiece3.png
willse_backgammon/Images/delete_icon.png
willse_backgammon/Images/delete_icon2.png
willse_backgammon/Images/delete_icon3.png
willse_backgammon/Images/exit_icon.png
willse_backgammon/Images/gear_icon.png
willse_backgammon/Images/lightPiece.png
willse_backgammon/Images/lightPiece2.png
willse_backgammon/Images/lightPiece3.png
willse_backgammon/Images/quit_icon.png
willse_backgammon/Images/restart_icon.png
willse_backgammon/Images/restart_icon2.png
willse_backgammon/Images/restart_icon3.png
willse_backgammon/Main_Files/AI.py
willse_backgammon/Main_Files/Graphics.py
willse_backgammon/Main_Files/Logic.py
willse_backgammon/Main_Files/Views.py
willse_backgammon/Main_Files/__init__.py
willse_backgammon/Main_Files/__pycache__/AI.cpython-310.pyc
willse_backgammon/Main_Files/__pycache__/Graphics.cpython-310.pyc
willse_backgammon/Main_Files/__pycache__/Logic.cpython-310.pyc
willse_backgammon/Main_Files/__pycache__/Views.cpython-310.pyc
willse_backgammon/Main_Files/__pycache__/__init__.cpython-310.pyc
willse_backgammon-0.0.2.dist-info/METADATA
willse_backgammon-0.0.2.dist-info/WHEEL
willse_backgammon-0.0.2.dist-info/entry_points.txt
willse_backgammon-0.0.2.dist-info/top_level.txt
willse_backgammon-0.0.2.dist-info/RECORD
